MANIFEST.in
Makefile
README.md
setup.cfg
setup.py
frameworks/pytorch/__init__.py
frameworks/pytorch/_version.py
frameworks/pytorch/base_rnn.py
frameworks/pytorch/gru.cc
frameworks/pytorch/gru.py
frameworks/pytorch/indrnn.cc
frameworks/pytorch/indrnn.py
frameworks/pytorch/layer_norm_gru.cc
frameworks/pytorch/layer_norm_gru.py
frameworks/pytorch/layer_norm_indrnn.cc
frameworks/pytorch/layer_norm_indrnn.py
frameworks/pytorch/layer_norm_lstm.cc
frameworks/pytorch/layer_norm_lstm.py
frameworks/pytorch/lstm.cc
frameworks/pytorch/lstm.py
frameworks/pytorch/support.cc
frameworks/pytorch/support.h
frameworks/tf/arena.h
frameworks/tf/gru.cc
frameworks/tf/indrnn.cc
frameworks/tf/layer_norm.cc
frameworks/tf/layer_norm_gru.cc
frameworks/tf/layer_norm_indrnn.cc
frameworks/tf/layer_norm_lstm.cc
frameworks/tf/lstm.cc
frameworks/tf/support.cc
frameworks/tf/support.h
haste_pytorch_cpu.egg-info/PKG-INFO
haste_pytorch_cpu.egg-info/SOURCES.txt
haste_pytorch_cpu.egg-info/dependency_links.txt
haste_pytorch_cpu.egg-info/top_level.txt
lib/blas.h
lib/device_assert.h
lib/gru_backward_gpu.cu.cc
lib/gru_forward_gpu.cu.cc
lib/haste.h
lib/indrnn_backward_gpu.cu.cc
lib/indrnn_forward_gpu.cu.cc
lib/inline_ops.h
lib/layer_norm_backward_gpu.cu.cc
lib/layer_norm_forward_gpu.cu.cc
lib/layer_norm_gru_backward_gpu.cu.cc
lib/layer_norm_gru_forward_gpu.cu.cc
lib/layer_norm_indrnn_backward_gpu.cu.cc
lib/layer_norm_indrnn_forward_gpu.cu.cc
lib/layer_norm_lstm_backward_gpu.cu.cc
lib/layer_norm_lstm_forward_gpu.cu.cc
lib/lstm_backward_gpu.cu.cc
lib/lstm_forward_gpu.cu.cc
lib/haste/gru.h
lib/haste/indrnn.h
lib/haste/layer_norm.h
lib/haste/layer_norm_gru.h
lib/haste/layer_norm_indrnn.h
lib/haste/layer_norm_lstm.h
lib/haste/lstm.h